LICENSE
MANIFEST.in
README.rst
pyproject.toml
setup.cfg
setup.py
pretix_regid/__init__.py
pretix_regid/apps.py
pretix_regid/models.py
pretix_regid/signals.py
pretix_regid/urls.py
pretix_regid/views.py
pretix_regid.egg-info/PKG-INFO
pretix_regid.egg-info/SOURCES.txt
pretix_regid.egg-info/dependency_links.txt
pretix_regid.egg-info/entry_points.txt
pretix_regid.egg-info/top_level.txt
pretix_regid/locale/de/LC_MESSAGES/django.mo
pretix_regid/locale/de/LC_MESSAGES/django.po
pretix_regid/locale/de_Informal/.gitkeep
pretix_regid/locale/de_Informal/LC_MESSAGES/django.mo
pretix_regid/locale/de_Informal/LC_MESSAGES/django.po
pretix_regid/migrations/0001_initial.py
pretix_regid/migrations/__init__.py
pretix_regid/static/pretix_regid/.gitkeep
pretix_regid/templates/pretix_regid/.gitkeep
pretix_regid/templates/pretix_regid/control_order_info.html
pretix_regid/templates/pretix_regid/order_info.html
pretix_regid/templates/pretix_regid/settings.html
tests/test_main.py