Metadata-Version: 2.1
Name: pretix-regid
Version: 0.1.5
Summary: Adds an automatic registration ID to approved orders
Author-email: "Christiaan de Die le Clercq (techwolf12)" <contact@techwolf12.nl>
Maintainer-email: "Christiaan de Die le Clercq (techwolf12)" <contact@techwolf12.nl>
License: 
Project-URL: homepage, https://github.com/techwolf12/pretix-regid
Keywords: pretix
License-File: LICENSE
